taskspec/__init__.py
taskspec-0.0.1.dev0.dist-info/METADATA
taskspec-0.0.1.dev0.dist-info/WHEEL
taskspec-0.0.1.dev0.dist-info/licenses/LICENSE
taskspec-0.0.1.dev0.dist-info/RECORD
